llama_index/readers/maps/__init__.py
llama_index/readers/maps/base.py
llama_index_readers_maps-0.4.1.dist-info/METADATA
llama_index_readers_maps-0.4.1.dist-info/WHEEL
llama_index_readers_maps-0.4.1.dist-info/licenses/LICENSE
llama_index_readers_maps-0.4.1.dist-info/RECORD
