Metadata-Version: 2.4
Name: llama-index-readers-maps
Version: 0.4.1
Summary: llama-index readers maps integration
Author-email: Your Name <you@example.com>
Maintainer: carrotpy
License-Expression: MIT
License-File: LICENSE
Keywords: geo,maps,open maps,open street maps,overpass api
Requires-Python: <4.0,>=3.9
Requires-Dist: geopy<3,>=2.4.1
Requires-Dist: llama-index-core<0.15,>=0.13.0
Requires-Dist: osmxtract<0.0.2,>=0.0.1
